qolab/__init__.py
qolab/atoms/__init__.py
qolab/atoms/rubidium/README.md
qolab/atoms/rubidium/__init__.py
qolab/atoms/rubidium/rubidium.py
qolab/data/__init__.py
qolab/data/trace.py
qolab/feedback/__init__.py
qolab/file_utils/__init__.py
qolab/gui/__init__.py
qolab/gui/web.py
qolab/hardware/__init__.py
qolab/hardware/basic.py
qolab/hardware/scpi.py
qolab/hardware/daq/__init__.py
qolab/hardware/daq/_basic.py
qolab/hardware/daq/labjack_ue9.py
qolab/hardware/i_server/__init__.py
qolab/hardware/i_server/i800.py
qolab/hardware/lockin/__init__.py
qolab/hardware/lockin/_basic.py
qolab/hardware/lockin/srs_sr865a.py
qolab/hardware/multimeter/__init__.py
qolab/hardware/multimeter/_basic.py
qolab/hardware/multimeter/bk_5491.py
qolab/hardware/multimeter/hp3457a.py
qolab/hardware/multimeter/hp_34401.py
qolab/hardware/power_supply/__init__.py
qolab/hardware/power_supply/_basic.py
qolab/hardware/power_supply/gpp3610h.py
qolab/hardware/power_supply/keysight_e3612a.py
qolab/hardware/power_supply/keysight_e36231a.py
qolab/hardware/power_supply/psw25045.py
qolab/hardware/rf_generator/__init__.py
qolab/hardware/rf_generator/_basic.py
qolab/hardware/rf_generator/agilent_e8257d.py
qolab/hardware/rf_generator/qol_lmx2487.py
qolab/hardware/scope/__init__.py
qolab/hardware/scope/_basic.py
qolab/hardware/scope/rigolds1054z.py
qolab/hardware/scope/sds1104x.py
qolab/hardware/scope/sds2304x.py
qolab/hardware/scope/sds800xhd.py
qolab/hardware/spectrum_analyzer/__init__.py
qolab/hardware/spectrum_analyzer/_basic.py
qolab/hardware/spectrum_analyzer/agilent_E4405B.py
qolab/hardware/vacuum_gauge/__init__.py
qolab/hardware/vacuum_gauge/mks390.py
qolab/math/__init__.py
qolab/math/spectral_utils.py
qolab/tableflow/__init__.py
qolab/tsdb/__init__.py
qolab-0.43.dist-info/licenses/LICENSE
qolab-0.43.dist-info/WHEEL
qolab-0.43.dist-info/METADATA
qolab-0.43.dist-info/RECORD
