Metadata-Version: 2.4
Name: qolab
Version: 0.43
Summary: Classes and functions useful for the quantum optics lab: qolab.
Keywords: scope,lockin,spectrum analyser,multimeter,DAQ,feedback,post processing
Author-email: "Eugeniy E. Mikhailov" <eemikh@wm.edu>
Maintainer-email: "Eugeniy E. Mikhailov" <eemikh@wm.edu>
Classifier: License :: OSI Approved :: GNU General Public License v3 or later (GPLv3+)
License-File: LICENSE
Requires-Dist: numpy >=1.19.5
Requires-Dist: matplotlib >=3.3.4
Requires-Dist: pyvisa >=1.11.3
Requires-Dist: scipy >=1.6.0
Requires-Dist: pyyaml >=5.3.1
Requires-Dist: justpy >= 0.2.3
Requires-Dist: pandas >= 1.1.5
Requires-Dist: starlette == 0.17.1; python_version <= '3.9'
Requires-Dist: starlette >= 0.17.1; python_version > '3.9'
Requires-Dist: universal_tsdb >=0.1.1
Requires-Dist: cachetools >=5.0.0
Requires-Dist: pyserial >= 3.4
Project-URL: Home, http://qo.physics.wm.edu/cgit/qolab.git/about/
